kbodatatools/__init__.py
kbodatatools/api.py
kbodatatools/basic_analysis.py
kbodatatools/datatools.py
kbodatatools/make_id.py
kbodatatools/patch.py
kbodatatools/save_scoreboard.py
kbodatatools/data/KBO_factor_list.csv
kbodatatools/data/KBO_full_data.h5
kbodatatools/data/KBO_gameid_full_season.csv
kbodatatools/data/KBO_player_info_full.csv
kbodatatools/data/patch_data_70820.csv
kbodatatools/data/patch_data_74556.csv
kbodatatools/data/patch_data_76100.csv
kbodatatools/data/patch_data_79535.csv
kbodatatools/data/patch_data_97109.csv
kbodatatools/data/patch_data_99137.csv
kbodatatools/data/renamed_player_list.csv
kbodatatools-0.0.1.dist-info/LICENSE
kbodatatools-0.0.1.dist-info/METADATA
kbodatatools-0.0.1.dist-info/WHEEL
kbodatatools-0.0.1.dist-info/top_level.txt
kbodatatools-0.0.1.dist-info/RECORD
