Metadata-Version: 2.1
Name: kbodatatools
Version: 0.0.1
Summary: KBO data wrangling & analysis tools
Home-page: https://github.com/LOPES-HUFS/kbodatatools
Author: Sunsick Choo
Author-email: sunsick_choo@naver.com
License: UNKNOWN
Platform: UNKNOWN
Classifier: Programming Language :: Python :: 3.6
Classifier: License :: OSI Approved :: GNU General Public License v3 (GPLv3)
Classifier: Operating System :: OS Independent
Requires-Python: >=3.6.0
Requires-Dist: pandas
Requires-Dist: requests-html
Requires-Dist: bs4
Requires-Dist: tables
Requires-Dist: datetime
